sagemaker_tensorflow/__init__.py
sagemaker_tensorflow/libPipeModeOp.so
sagemaker_tensorflow/pipemode.py
sagemaker_tensorflow-2.14.0.1.20.0.dist-info/LICENSE
sagemaker_tensorflow-2.14.0.1.20.0.dist-info/METADATA
sagemaker_tensorflow-2.14.0.1.20.0.dist-info/NOTICE
sagemaker_tensorflow-2.14.0.1.20.0.dist-info/WHEEL
sagemaker_tensorflow-2.14.0.1.20.0.dist-info/top_level.txt
sagemaker_tensorflow-2.14.0.1.20.0.dist-info/RECORD
