Metadata-Version: 2.1
Name: sagemaker-tensorflow
Version: 2.14.0.1.20.0
Summary: Amazon Sagemaker specific TensorFlow extensions.
Home-page: https://github.com/aws/sagemaker-tensorflow
Author: Amazon Web Services
Maintainer: Amazon Web Services
License: Apache License 2.0
Platform: UNKNOWN
Classifier: Development Status :: 5 - Production/Stable
Classifier: Intended Audience :: Developers
Classifier: Natural Language :: English
Classifier: License :: OSI Approved :: Apache Software License
Classifier: Programming Language :: Python
Classifier: Programming Language :: Python :: 3.9
Classifier: Programming Language :: Python :: 3.10
Requires-Python: >= 3.9
License-File: LICENSE
License-File: NOTICE
Provides-Extra: test
Requires-Dist: tox ; extra == 'test'
Requires-Dist: flake8 ; extra == 'test'
Requires-Dist: pytest ; extra == 'test'
Requires-Dist: pytest-cov ; extra == 'test'
Requires-Dist: pytest-xdist ; extra == 'test'
Requires-Dist: mock ; extra == 'test'
Requires-Dist: sagemaker ; extra == 'test'
Requires-Dist: docker ; extra == 'test'
Requires-Dist: boto3 ; extra == 'test'
